{"coref": [[[["he", 0, 6, 6, 7], ["Tom", 0, 0, 0, 1]], [["he", 1, 5, 5, 6], ["Tom", 0, 0, 0, 1]]], [[["the balloons", 0, 2, 11, 13], ["30 violet balloons", 0, 4, 2, 5]]]], "sentences": [{"parsetree": "(ROOT (S (S (NP (NNP Tom)) (VP (VBZ has) (NP (CD 30) (NN violet) (NNS balloons)))) (, ,) (NP (PRP he)) (VP (VBD gave) (NP (NP (NNP Fred) (CD 16)) (PP (IN of) (NP (DT the) (NNS balloons))))) (. .)))", "text": "Tom has 30 violet balloons , he gave Fred 16 of the balloons .", "dependencies": [["root", "ROOT", "gave"], ["nsubj", "has", "Tom"], ["ccomp", "gave", "has"], ["num", "balloons", "30"], ["nn", "balloons", "violet"], ["dobj", "has", "balloons"], ["nsubj", "gave", "he"], ["dobj", "gave", "Fred"], ["num", "Fred", "16"], ["det", "balloons", "the"], ["prep_of", "Fred", "balloons"]], "words": [["Tom", {"NamedEntityTag": "PERSON", "CharacterOffsetEnd": "3", "CharacterOffsetBegin": "0", "PartOfSpeech": "NNP", "Lemma": "Tom"}], ["has", {"NamedEntityTag": "O", "CharacterOffsetEnd": "7", "CharacterOffsetBegin": "4", "PartOfSpeech": "VBZ", "Lemma": "have"}], ["30", {"NormalizedNamedEntityTag": "30.0", "Lemma": "30", "CharacterOffsetEnd": "10", "PartOfSpeech": "CD", "CharacterOffsetBegin": "8", "NamedEntityTag": "NUMBER"}], ["violet", {"NamedEntityTag": "O", "CharacterOffsetEnd": "17", "CharacterOffsetBegin": "11", "PartOfSpeech": "NN", "Lemma": "violet"}], ["balloons", {"NamedEntityTag": "O", "CharacterOffsetEnd": "26", "CharacterOffsetBegin": "18", "PartOfSpeech": "NNS", "Lemma": "balloon"}], [",", {"NamedEntityTag": "O", "CharacterOffsetEnd": "28", "CharacterOffsetBegin": "27", "PartOfSpeech": ",", "Lemma": ","}], ["he", {"NamedEntityTag": "O", "CharacterOffsetEnd": "31", "CharacterOffsetBegin": "29", "PartOfSpeech": "PRP", "Lemma": "he"}], ["gave", {"NamedEntityTag": "O", "CharacterOffsetEnd": "36", "CharacterOffsetBegin": "32", "PartOfSpeech": "VBD", "Lemma": "give"}], ["Fred", {"NamedEntityTag": "PERSON", "CharacterOffsetEnd": "41", "CharacterOffsetBegin": "37", "PartOfSpeech": "NNP", "Lemma": "Fred"}], ["16", {"NormalizedNamedEntityTag": "16.0", "Lemma": "16", "CharacterOffsetEnd": "44", "PartOfSpeech": "CD", "CharacterOffsetBegin": "42", "NamedEntityTag": "NUMBER"}], ["of", {"NamedEntityTag": "O", "CharacterOffsetEnd": "47", "CharacterOffsetBegin": "45", "PartOfSpeech": "IN", "Lemma": "of"}], ["the", {"NamedEntityTag": "O", "CharacterOffsetEnd": "51", "CharacterOffsetBegin": "48", "PartOfSpeech": "DT", "Lemma": "the"}], ["balloons", {"NamedEntityTag": "O", "CharacterOffsetEnd": "60", "CharacterOffsetBegin": "52", "PartOfSpeech": "NNS", "Lemma": "balloon"}], [".", {"NamedEntityTag": "O", "CharacterOffsetEnd": "62", "CharacterOffsetBegin": "61", "PartOfSpeech": ".", "Lemma": "."}]]}, {"parsetree": "(ROOT (SBARQ (WHNP (WHADJP (WRB How) (JJ many)) (NN violet) (NNS balloons)) (SQ (VP (VBZ does) (SBAR (S (NP (PRP he)) (ADVP (RB now)) (VP (VBP have)))))) (. ?)))", "text": "How many violet balloons does he now have ?", "dependencies": [["root", "ROOT", "does"], ["advmod", "many", "How"], ["amod", "balloons", "many"], ["nn", "balloons", "violet"], ["nsubj", "does", "balloons"], ["nsubj", "have", "he"], ["advmod", "have", "now"], ["ccomp", "does", "have"]], "words": [["How", {"NamedEntityTag": "O", "CharacterOffsetEnd": "66", "CharacterOffsetBegin": "63", "PartOfSpeech": "WRB", "Lemma": "how"}], ["many", {"NamedEntityTag": "O", "CharacterOffsetEnd": "71", "CharacterOffsetBegin": "67", "PartOfSpeech": "JJ", "Lemma": "many"}], ["violet", {"NamedEntityTag": "O", "CharacterOffsetEnd": "78", "CharacterOffsetBegin": "72", "PartOfSpeech": "NN", "Lemma": "violet"}], ["balloons", {"NamedEntityTag": "O", "CharacterOffsetEnd": "87", "CharacterOffsetBegin": "79", "PartOfSpeech": "NNS", "Lemma": "balloon"}], ["does", {"NamedEntityTag": "O", "CharacterOffsetEnd": "92", "CharacterOffsetBegin": "88", "PartOfSpeech": "VBZ", "Lemma": "do"}], ["he", {"NamedEntityTag": "O", "CharacterOffsetEnd": "95", "CharacterOffsetBegin": "93", "PartOfSpeech": "PRP", "Lemma": "he"}], ["now", {"NormalizedNamedEntityTag": "PRESENT_REF", "Timex": "<TIMEX3 tid=\"t1\" type=\"DATE\" value=\"PRESENT_REF\">now</TIMEX3>", "Lemma": "now", "CharacterOffsetEnd": "99", "PartOfSpeech": "RB", "CharacterOffsetBegin": "96", "NamedEntityTag": "DATE"}], ["have", {"NamedEntityTag": "O", "CharacterOffsetEnd": "104", "CharacterOffsetBegin": "100", "PartOfSpeech": "VBP", "Lemma": "have"}], ["?", {"NamedEntityTag": "O", "CharacterOffsetEnd": "106", "CharacterOffsetBegin": "105", "PartOfSpeech": ".", "Lemma": "?"}]]}]}