{"coref": [[[["Mary", 1, 0, 0, 1], ["Mary", 0, 0, 0, 1]], [["she", 2, 7, 7, 8], ["Mary", 0, 0, 0, 1]]]], "sentences": [{"parsetree": "(ROOT (S (NP (NNP Mary)) (VP (VBZ loves) (S (VP (VBG eating) (NP (NNS fruits))))) (. .)))", "text": "Mary loves eating fruits .", "dependencies": [["root", "ROOT", "loves"], ["nsubj", "loves", "Mary"], ["xcomp", "loves", "eating"], ["dobj", "eating", "fruits"]], "words": [["Mary", {"NamedEntityTag": "PERSON", "CharacterOffsetEnd": "4", "CharacterOffsetBegin": "0", "PartOfSpeech": "NNP", "Lemma": "Mary"}], ["loves", {"NamedEntityTag": "O", "CharacterOffsetEnd": "10", "CharacterOffsetBegin": "5", "PartOfSpeech": "VBZ", "Lemma": "love"}], ["eating", {"NamedEntityTag": "O", "CharacterOffsetEnd": "17", "CharacterOffsetBegin": "11", "PartOfSpeech": "VBG", "Lemma": "eat"}], ["fruits", {"NamedEntityTag": "O", "CharacterOffsetEnd": "24", "CharacterOffsetBegin": "18", "PartOfSpeech": "NNS", "Lemma": "fruit"}], [".", {"NamedEntityTag": "O", "CharacterOffsetEnd": "26", "CharacterOffsetBegin": "25", "PartOfSpeech": ".", "Lemma": "."}]]}, {"parsetree": "(ROOT (S (NP (NNP Mary)) (VP (VBD paid) (NP (NP (NP ($ $) (CD 11.08)) (PP (IN for) (NP (NNS berries)))) (, ,) (NP (NP ($ $) (CD 14.33)) (PP (IN for) (NP (NNS apples)))) (, ,) (CC and) (NP (NP ($ $) (CD 9.31)) (PP (IN for) (NP (NNS peaches)))))) (. .)))", "text": "Mary paid $ 11.08 for berries , $ 14.33 for apples , and $ 9.31 for peaches .", "dependencies": [["root", "ROOT", "paid"], ["nsubj", "paid", "Mary"], ["dobj", "paid", "$"], ["num", "$", "11.08"], ["prep_for", "$", "berries"], ["conj_and", "$", "$"], ["num", "$", "14.33"], ["prep_for", "$", "apples"], ["conj_and", "$", "$"], ["num", "$", "9.31"], ["prep_for", "$", "peaches"]], "words": [["Mary", {"NamedEntityTag": "PERSON", "CharacterOffsetEnd": "31", "CharacterOffsetBegin": "27", "PartOfSpeech": "NNP", "Lemma": "Mary"}], ["paid", {"NamedEntityTag": "O", "CharacterOffsetEnd": "36", "CharacterOffsetBegin": "32", "PartOfSpeech": "VBD", "Lemma": "pay"}], ["$", {"NormalizedNamedEntityTag": "$11.08", "Lemma": "$", "CharacterOffsetEnd": "38", "PartOfSpeech": "$", "CharacterOffsetBegin": "37", "NamedEntityTag": "MONEY"}], ["11.08", {"NormalizedNamedEntityTag": "$11.08", "Lemma": "11.08", "CharacterOffsetEnd": "44", "PartOfSpeech": "CD", "CharacterOffsetBegin": "39", "NamedEntityTag": "MONEY"}], ["for", {"NamedEntityTag": "O", "CharacterOffsetEnd": "48", "CharacterOffsetBegin": "45", "PartOfSpeech": "IN", "Lemma": "for"}], ["berries", {"NamedEntityTag": "O", "CharacterOffsetEnd": "56", "CharacterOffsetBegin": "49", "PartOfSpeech": "NNS", "Lemma": "berry"}], [",", {"NamedEntityTag": "O", "CharacterOffsetEnd": "58", "CharacterOffsetBegin": "57", "PartOfSpeech": ",", "Lemma": ","}], ["$", {"NormalizedNamedEntityTag": "$14.33", "Lemma": "$", "CharacterOffsetEnd": "60", "PartOfSpeech": "$", "CharacterOffsetBegin": "59", "NamedEntityTag": "MONEY"}], ["14.33", {"NormalizedNamedEntityTag": "$14.33", "Lemma": "14.33", "CharacterOffsetEnd": "66", "PartOfSpeech": "CD", "CharacterOffsetBegin": "61", "NamedEntityTag": "MONEY"}], ["for", {"NamedEntityTag": "O", "CharacterOffsetEnd": "70", "CharacterOffsetBegin": "67", "PartOfSpeech": "IN", "Lemma": "for"}], ["apples", {"NamedEntityTag": "O", "CharacterOffsetEnd": "77", "CharacterOffsetBegin": "71", "PartOfSpeech": "NNS", "Lemma": "apple"}], [",", {"NamedEntityTag": "O", "CharacterOffsetEnd": "79", "CharacterOffsetBegin": "78", "PartOfSpeech": ",", "Lemma": ","}], ["and", {"NamedEntityTag": "O", "CharacterOffsetEnd": "83", "CharacterOffsetBegin": "80", "PartOfSpeech": "CC", "Lemma": "and"}], ["$", {"NormalizedNamedEntityTag": "$9.31", "Lemma": "$", "CharacterOffsetEnd": "85", "PartOfSpeech": "$", "CharacterOffsetBegin": "84", "NamedEntityTag": "MONEY"}], ["9.31", {"NormalizedNamedEntityTag": "$9.31", "Lemma": "9.31", "CharacterOffsetEnd": "90", "PartOfSpeech": "CD", "CharacterOffsetBegin": "86", "NamedEntityTag": "MONEY"}], ["for", {"NamedEntityTag": "O", "CharacterOffsetEnd": "94", "CharacterOffsetBegin": "91", "PartOfSpeech": "IN", "Lemma": "for"}], ["peaches", {"NamedEntityTag": "O", "CharacterOffsetEnd": "102", "CharacterOffsetBegin": "95", "PartOfSpeech": "NNS", "Lemma": "peach"}], [".", {"NamedEntityTag": "O", "CharacterOffsetEnd": "104", "CharacterOffsetBegin": "103", "PartOfSpeech": ".", "Lemma": "."}]]}, {"parsetree": "(ROOT (SBARQ (PP (IN In) (NP (NN total))) (, ,) (WHNP (WHADJP (WRB how) (JJ much)) (NN money)) (SQ (VBD did) (NP (PRP she)) (VP (VB spend))) (. ?)))", "text": "In total , how much money did she spend ?", "dependencies": [["root", "ROOT", "spend"], ["prep_in", "spend", "total"], ["advmod", "much", "how"], ["amod", "money", "much"], ["dobj", "spend", "money"], ["aux", "spend", "did"], ["nsubj", "spend", "she"]], "words": [["In", {"NamedEntityTag": "O", "CharacterOffsetEnd": "107", "CharacterOffsetBegin": "105", "PartOfSpeech": "IN", "Lemma": "in"}], ["total", {"NamedEntityTag": "O", "CharacterOffsetEnd": "113", "CharacterOffsetBegin": "108", "PartOfSpeech": "NN", "Lemma": "total"}], [",", {"NamedEntityTag": "O", "CharacterOffsetEnd": "115", "CharacterOffsetBegin": "114", "PartOfSpeech": ",", "Lemma": ","}], ["how", {"NamedEntityTag": "O", "CharacterOffsetEnd": "119", "CharacterOffsetBegin": "116", "PartOfSpeech": "WRB", "Lemma": "how"}], ["much", {"NamedEntityTag": "O", "CharacterOffsetEnd": "124", "CharacterOffsetBegin": "120", "PartOfSpeech": "JJ", "Lemma": "much"}], ["money", {"NamedEntityTag": "O", "CharacterOffsetEnd": "130", "CharacterOffsetBegin": "125", "PartOfSpeech": "NN", "Lemma": "money"}], ["did", {"NamedEntityTag": "O", "CharacterOffsetEnd": "134", "CharacterOffsetBegin": "131", "PartOfSpeech": "VBD", "Lemma": "do"}], ["she", {"NamedEntityTag": "O", "CharacterOffsetEnd": "138", "CharacterOffsetBegin": "135", "PartOfSpeech": "PRP", "Lemma": "she"}], ["spend", {"NamedEntityTag": "O", "CharacterOffsetEnd": "144", "CharacterOffsetBegin": "139", "PartOfSpeech": "VB", "Lemma": "spend"}], ["?", {"NamedEntityTag": "O", "CharacterOffsetEnd": "146", "CharacterOffsetBegin": "145", "PartOfSpeech": ".", "Lemma": "?"}]]}]}