{"sentences": [{"parsetree": "(ROOT (S (ADVP (RB So) (RB far)) (, ,) (NP (DT an) (NN orchard)) (VP (VBZ has) (VP (VBN sold) (NP (NP (DT a) (JJ combined) (NN total)) (PP (IN of) (NP (NP (CD 9792) (NNS pounds)) (PP (IN of) (NP (ADJP (JJ fresh) (CC and) (JJ frozen)) (NN fruit))) (NP-TMP (DT this) (NN season))))))) (. .)))", "text": "So far , an orchard has sold a combined total of 9792 pounds of fresh and frozen fruit this season .", "dependencies": [["root", "ROOT", "sold"], ["advmod", "far", "So"], ["advmod", "sold", "far"], ["det", "orchard", "an"], ["nsubj", "sold", "orchard"], ["aux", "sold", "has"], ["det", "total", "a"], ["amod", "total", "combined"], ["dobj", "sold", "total"], ["num", "pounds", "9792"], ["prep_of", "total", "pounds"], ["amod", "fruit", "fresh"], ["conj_and", "fresh", "frozen"], ["prep_of", "pounds", "fruit"], ["det", "season", "this"], ["tmod", "pounds", "season"]], "words": [["So", {"NamedEntityTag": "O", "CharacterOffsetEnd": "2", "CharacterOffsetBegin": "0", "PartOfSpeech": "RB", "Lemma": "so"}], ["far", {"NamedEntityTag": "O", "CharacterOffsetEnd": "6", "CharacterOffsetBegin": "3", "PartOfSpeech": "RB", "Lemma": "far"}], [",", {"NamedEntityTag": "O", "CharacterOffsetEnd": "8", "CharacterOffsetBegin": "7", "PartOfSpeech": ",", "Lemma": ","}], ["an", {"NamedEntityTag": "O", "CharacterOffsetEnd": "11", "CharacterOffsetBegin": "9", "PartOfSpeech": "DT", "Lemma": "a"}], ["orchard", {"NamedEntityTag": "O", "CharacterOffsetEnd": "19", "CharacterOffsetBegin": "12", "PartOfSpeech": "NN", "Lemma": "orchard"}], ["has", {"NamedEntityTag": "O", "CharacterOffsetEnd": "23", "CharacterOffsetBegin": "20", "PartOfSpeech": "VBZ", "Lemma": "have"}], ["sold", {"NamedEntityTag": "O", "CharacterOffsetEnd": "28", "CharacterOffsetBegin": "24", "PartOfSpeech": "VBN", "Lemma": "sell"}], ["a", {"NamedEntityTag": "O", "CharacterOffsetEnd": "30", "CharacterOffsetBegin": "29", "PartOfSpeech": "DT", "Lemma": "a"}], ["combined", {"NamedEntityTag": "O", "CharacterOffsetEnd": "39", "CharacterOffsetBegin": "31", "PartOfSpeech": "JJ", "Lemma": "combined"}], ["total", {"NamedEntityTag": "O", "CharacterOffsetEnd": "45", "CharacterOffsetBegin": "40", "PartOfSpeech": "NN", "Lemma": "total"}], ["of", {"NamedEntityTag": "O", "CharacterOffsetEnd": "48", "CharacterOffsetBegin": "46", "PartOfSpeech": "IN", "Lemma": "of"}], ["9792", {"NormalizedNamedEntityTag": "9792", "Lemma": "9792", "CharacterOffsetEnd": "53", "PartOfSpeech": "CD", "CharacterOffsetBegin": "49", "NamedEntityTag": "DATE"}], ["pounds", {"NormalizedNamedEntityTag": "\u00a3", "Lemma": "pound", "CharacterOffsetEnd": "60", "PartOfSpeech": "NNS", "CharacterOffsetBegin": "54", "NamedEntityTag": "MONEY"}], ["of", {"NamedEntityTag": "O", "CharacterOffsetEnd": "63", "CharacterOffsetBegin": "61", "PartOfSpeech": "IN", "Lemma": "of"}], ["fresh", {"NamedEntityTag": "O", "CharacterOffsetEnd": "69", "CharacterOffsetBegin": "64", "PartOfSpeech": "JJ", "Lemma": "fresh"}], ["and", {"NamedEntityTag": "O", "CharacterOffsetEnd": "73", "CharacterOffsetBegin": "70", "PartOfSpeech": "CC", "Lemma": "and"}], ["frozen", {"NamedEntityTag": "O", "CharacterOffsetEnd": "80", "CharacterOffsetBegin": "74", "PartOfSpeech": "JJ", "Lemma": "frozen"}], ["fruit", {"NamedEntityTag": "O", "CharacterOffsetEnd": "86", "CharacterOffsetBegin": "81", "PartOfSpeech": "NN", "Lemma": "fruit"}], ["this", {"NamedEntityTag": "O", "CharacterOffsetEnd": "91", "CharacterOffsetBegin": "87", "PartOfSpeech": "DT", "Lemma": "this"}], ["season", {"NamedEntityTag": "O", "CharacterOffsetEnd": "98", "CharacterOffsetBegin": "92", "PartOfSpeech": "NN", "Lemma": "season"}], [".", {"NamedEntityTag": "O", "CharacterOffsetEnd": "100", "CharacterOffsetBegin": "99", "PartOfSpeech": ".", "Lemma": "."}]]}, {"parsetree": "(ROOT (SBARQ (SBAR (IN If) (S (NP (PRP they)) (VP (VBP have) (VP (VBN sold) (NP (NP (CD 3513) (NNS pounds)) (PP (IN of) (NP (JJ frozen) (NN fruit)))))))) (, ,) (WHNP (WHNP (WHADJP (WRB how) (JJ many)) (NNS pounds)) (PP (IN of) (NP (JJ fresh) (NN fruit)))) (SQ (VP (VBP have) (VP (VBN been) (VP (VBN sold) (ADVP (RB so) (RB far)))))) (. ?)))", "text": "If they have sold 3513 pounds of frozen fruit , how many pounds of fresh fruit have been sold so far ?", "dependencies": [["root", "ROOT", "sold"], ["mark", "sold", "If"], ["nsubj", "sold", "they"], ["aux", "sold", "have"], ["advcl", "sold", "sold"], ["num", "pounds", "3513"], ["dobj", "sold", "pounds"], ["amod", "fruit", "frozen"], ["prep_of", "pounds", "fruit"], ["advmod", "many", "how"], ["amod", "pounds", "many"], ["nsubjpass", "sold", "pounds"], ["amod", "fruit", "fresh"], ["prep_of", "pounds", "fruit"], ["aux", "sold", "have"], ["auxpass", "sold", "been"], ["advmod", "far", "so"], ["advmod", "sold", "far"]], "words": [["If", {"NamedEntityTag": "O", "CharacterOffsetEnd": "103", "CharacterOffsetBegin": "101", "PartOfSpeech": "IN", "Lemma": "if"}], ["they", {"NamedEntityTag": "O", "CharacterOffsetEnd": "108", "CharacterOffsetBegin": "104", "PartOfSpeech": "PRP", "Lemma": "they"}], ["have", {"NamedEntityTag": "O", "CharacterOffsetEnd": "113", "CharacterOffsetBegin": "109", "PartOfSpeech": "VBP", "Lemma": "have"}], ["sold", {"NamedEntityTag": "O", "CharacterOffsetEnd": "118", "CharacterOffsetBegin": "114", "PartOfSpeech": "VBN", "Lemma": "sell"}], ["3513", {"NormalizedNamedEntityTag": "3513", "Lemma": "3513", "CharacterOffsetEnd": "123", "PartOfSpeech": "CD", "CharacterOffsetBegin": "119", "NamedEntityTag": "DATE"}], ["pounds", {"NormalizedNamedEntityTag": "\u00a3", "Lemma": "pound", "CharacterOffsetEnd": "130", "PartOfSpeech": "NNS", "CharacterOffsetBegin": "124", "NamedEntityTag": "MONEY"}], ["of", {"NamedEntityTag": "O", "CharacterOffsetEnd": "133", "CharacterOffsetBegin": "131", "PartOfSpeech": "IN", "Lemma": "of"}], ["frozen", {"NamedEntityTag": "O", "CharacterOffsetEnd": "140", "CharacterOffsetBegin": "134", "PartOfSpeech": "JJ", "Lemma": "frozen"}], ["fruit", {"NamedEntityTag": "O", "CharacterOffsetEnd": "146", "CharacterOffsetBegin": "141", "PartOfSpeech": "NN", "Lemma": "fruit"}], [",", {"NamedEntityTag": "O", "CharacterOffsetEnd": "148", "CharacterOffsetBegin": "147", "PartOfSpeech": ",", "Lemma": ","}], ["how", {"NamedEntityTag": "O", "CharacterOffsetEnd": "152", "CharacterOffsetBegin": "149", "PartOfSpeech": "WRB", "Lemma": "how"}], ["many", {"NamedEntityTag": "O", "CharacterOffsetEnd": "157", "CharacterOffsetBegin": "153", "PartOfSpeech": "JJ", "Lemma": "many"}], ["pounds", {"NamedEntityTag": "O", "CharacterOffsetEnd": "164", "CharacterOffsetBegin": "158", "PartOfSpeech": "NNS", "Lemma": "pound"}], ["of", {"NamedEntityTag": "O", "CharacterOffsetEnd": "167", "CharacterOffsetBegin": "165", "PartOfSpeech": "IN", "Lemma": "of"}], ["fresh", {"NamedEntityTag": "O", "CharacterOffsetEnd": "173", "CharacterOffsetBegin": "168", "PartOfSpeech": "JJ", "Lemma": "fresh"}], ["fruit", {"NamedEntityTag": "O", "CharacterOffsetEnd": "179", "CharacterOffsetBegin": "174", "PartOfSpeech": "NN", "Lemma": "fruit"}], ["have", {"NamedEntityTag": "O", "CharacterOffsetEnd": "184", "CharacterOffsetBegin": "180", "PartOfSpeech": "VBP", "Lemma": "have"}], ["been", {"NamedEntityTag": "O", "CharacterOffsetEnd": "189", "CharacterOffsetBegin": "185", "PartOfSpeech": "VBN", "Lemma": "be"}], ["sold", {"NamedEntityTag": "O", "CharacterOffsetEnd": "194", "CharacterOffsetBegin": "190", "PartOfSpeech": "VBN", "Lemma": "sell"}], ["so", {"NamedEntityTag": "O", "CharacterOffsetEnd": "197", "CharacterOffsetBegin": "195", "PartOfSpeech": "RB", "Lemma": "so"}], ["far", {"NamedEntityTag": "O", "CharacterOffsetEnd": "201", "CharacterOffsetBegin": "198", "PartOfSpeech": "RB", "Lemma": "far"}], ["?", {"NamedEntityTag": "O", "CharacterOffsetEnd": "203", "CharacterOffsetBegin": "202", "PartOfSpeech": ".", "Lemma": "?"}]]}]}