{"coref": [[[["they", 2, 4, 4, 5], ["38 cantelopes", 0, 6, 5, 7]]]], "sentences": [{"parsetree": "(ROOT (S (NP (NNP Dan)) (VP (VBD grew) (NP (NP (CD 42) (NNS turnips)) (CC and) (NP (CD 38) (NNS cantelopes)))) (. .)))", "text": "Dan grew 42 turnips and 38 cantelopes .", "dependencies": [["root", "ROOT", "grew"], ["nsubj", "grew", "Dan"], ["num", "turnips", "42"], ["dobj", "grew", "turnips"], ["num", "cantelopes", "38"], ["conj_and", "turnips", "cantelopes"]], "words": [["Dan", {"NamedEntityTag": "PERSON", "CharacterOffsetEnd": "3", "CharacterOffsetBegin": "0", "PartOfSpeech": "NNP", "Lemma": "Dan"}], ["grew", {"NamedEntityTag": "O", "CharacterOffsetEnd": "8", "CharacterOffsetBegin": "4", "PartOfSpeech": "VBD", "Lemma": "grow"}], ["42", {"NormalizedNamedEntityTag": "42.0", "Lemma": "42", "CharacterOffsetEnd": "11", "PartOfSpeech": "CD", "CharacterOffsetBegin": "9", "NamedEntityTag": "NUMBER"}], ["turnips", {"NamedEntityTag": "O", "CharacterOffsetEnd": "19", "CharacterOffsetBegin": "12", "PartOfSpeech": "NNS", "Lemma": "turnip"}], ["and", {"NamedEntityTag": "O", "CharacterOffsetEnd": "23", "CharacterOffsetBegin": "20", "PartOfSpeech": "CC", "Lemma": "and"}], ["38", {"NormalizedNamedEntityTag": "38.0", "Lemma": "38", "CharacterOffsetEnd": "26", "PartOfSpeech": "CD", "CharacterOffsetBegin": "24", "NamedEntityTag": "NUMBER"}], ["cantelopes", {"NamedEntityTag": "O", "CharacterOffsetEnd": "37", "CharacterOffsetBegin": "27", "PartOfSpeech": "NNS", "Lemma": "cantelope"}], [".", {"NamedEntityTag": "O", "CharacterOffsetEnd": "39", "CharacterOffsetBegin": "38", "PartOfSpeech": ".", "Lemma": "."}]]}, {"parsetree": "(ROOT (S (NP (NNP Jessica)) (VP (VBD grew) (NP (CD 47) (NNS turnips))) (. .)))", "text": "Jessica grew 47 turnips .", "dependencies": [["root", "ROOT", "grew"], ["nsubj", "grew", "Jessica"], ["num", "turnips", "47"], ["dobj", "grew", "turnips"]], "words": [["Jessica", {"NamedEntityTag": "PERSON", "CharacterOffsetEnd": "47", "CharacterOffsetBegin": "40", "PartOfSpeech": "NNP", "Lemma": "Jessica"}], ["grew", {"NamedEntityTag": "O", "CharacterOffsetEnd": "52", "CharacterOffsetBegin": "48", "PartOfSpeech": "VBD", "Lemma": "grow"}], ["47", {"NormalizedNamedEntityTag": "47.0", "Lemma": "47", "CharacterOffsetEnd": "55", "PartOfSpeech": "CD", "CharacterOffsetBegin": "53", "NamedEntityTag": "NUMBER"}], ["turnips", {"NamedEntityTag": "O", "CharacterOffsetEnd": "63", "CharacterOffsetBegin": "56", "PartOfSpeech": "NNS", "Lemma": "turnip"}], [".", {"NamedEntityTag": "O", "CharacterOffsetEnd": "65", "CharacterOffsetBegin": "64", "PartOfSpeech": ".", "Lemma": "."}]]}, {"parsetree": "(ROOT (SBARQ (WHADVP (WRB How) (NP (JJ many) (NNS turnips))) (SQ (VBD did) (NP (PRP they)) (VP (VB grow) (PP (IN in) (NP (NN total))))) (. ?)))", "text": "How many turnips did they grow in total ?", "dependencies": [["root", "ROOT", "grow"], ["advmod", "grow", "How"], ["amod", "turnips", "many"], ["dep", "How", "turnips"], ["aux", "grow", "did"], ["nsubj", "grow", "they"], ["prep_in", "grow", "total"]], "words": [["How", {"NamedEntityTag": "O", "CharacterOffsetEnd": "69", "CharacterOffsetBegin": "66", "PartOfSpeech": "WRB", "Lemma": "how"}], ["many", {"NamedEntityTag": "O", "CharacterOffsetEnd": "74", "CharacterOffsetBegin": "70", "PartOfSpeech": "JJ", "Lemma": "many"}], ["turnips", {"NamedEntityTag": "O", "CharacterOffsetEnd": "82", "CharacterOffsetBegin": "75", "PartOfSpeech": "NNS", "Lemma": "turnip"}], ["did", {"NamedEntityTag": "O", "CharacterOffsetEnd": "86", "CharacterOffsetBegin": "83", "PartOfSpeech": "VBD", "Lemma": "do"}], ["they", {"NamedEntityTag": "O", "CharacterOffsetEnd": "91", "CharacterOffsetBegin": "87", "PartOfSpeech": "PRP", "Lemma": "they"}], ["grow", {"NamedEntityTag": "O", "CharacterOffsetEnd": "96", "CharacterOffsetBegin": "92", "PartOfSpeech": "VB", "Lemma": "grow"}], ["in", {"NamedEntityTag": "O", "CharacterOffsetEnd": "99", "CharacterOffsetBegin": "97", "PartOfSpeech": "IN", "Lemma": "in"}], ["total", {"NamedEntityTag": "O", "CharacterOffsetEnd": "105", "CharacterOffsetBegin": "100", "PartOfSpeech": "NN", "Lemma": "total"}], ["?", {"NamedEntityTag": "O", "CharacterOffsetEnd": "107", "CharacterOffsetBegin": "106", "PartOfSpeech": ".", "Lemma": "?"}]]}]}